promql_builder/__init__.py
promql_builder/builders/__init__.py
promql_builder/builders/promql.py
promql_builder/cog/__init__.py
promql_builder/cog/builder.py
promql_builder/cog/encoder.py
promql_builder/models/__init__.py
promql_builder/models/promql.py
promql_builder-0.0.4.dist-info/METADATA
promql_builder-0.0.4.dist-info/WHEEL
promql_builder-0.0.4.dist-info/RECORD
