Metadata-Version: 2.4
Name: promql_builder
Version: 0.0.4
Summary: Library to compose PromQL queries in Python.
Project-URL: Homepage, https://github.com/grafana/promql-builder
Project-URL: Repository, https://github.com/grafana/promql-builder.git
Project-URL: Issues, https://github.com/grafana/promql-builder/issues
Author: Grafana Labs
Keywords: builder,observability,prometheus,promql
Classifier: Development Status :: 3 - Alpha
Classifier: Intended Audience :: Developers
Classifier: Intended Audience :: System Administrators
Classifier: License :: OSI Approved :: Apache Software License
Classifier: Operating System :: OS Independent
Classifier: Programming Language :: Python :: 3.11
Classifier: Programming Language :: Python :: 3.12
Classifier: Topic :: Software Development :: Libraries
Classifier: Topic :: System :: Monitoring
Requires-Python: >=3.11
